aitomatic/__init__.py
aitomatic/api/__init__.py
aitomatic/api/build.py
aitomatic/api/client.py
aitomatic/api/exceptions.py
aitomatic/api/model_params.py
aitomatic/api/tuning_utils.py
aitomatic/api/web_model.py
aitomatic/dsl/__init__.py
aitomatic/dsl/arl_conclusions.py
aitomatic/dsl/arl_features.py
aitomatic/dsl/arl_handler.py
aitomatic/dsl/arl_rules.py
aitomatic/dsl/utils.py
aitomatic/objects/__init__.py
aitomatic/objects/dataset.py
aitomatic/objects/model.py
aitomatic-1.3.1.dist-info/LICENSE
aitomatic-1.3.1.dist-info/METADATA
aitomatic-1.3.1.dist-info/WHEEL
aitomatic-1.3.1.dist-info/top_level.txt
aitomatic-1.3.1.dist-info/RECORD
