Metadata-Version: 2.1
Name: aitomatic
Version: 1.3.1
Summary: aitomatic library to interact with Aitomatic product
Home-page: https://github.com/aitomatic/aitomatic-cli
Author: Pham Hoang Tuan
Author-email: tuan@aitomatic.com
Project-URL: Bug Tracker, https://github.com/aitomatic/aitomatic-cli/issues
Classifier: Programming Language :: Python :: 3.8
Classifier: License :: OSI Approved :: MIT License
Classifier: Operating System :: OS Independent
Requires-Python: >=3.7
License-File: LICENSE
Requires-Dist: tqdm (>=4.64.1)
Requires-Dist: requests (>=2.27)
Requires-Dist: numpy (>=1.23.4)
Requires-Dist: pandas (>=1.5.1)
Requires-Dist: fastparquet (>=2023.4.0)
